ffb/__init__.py
ffb/core/__init__.py
ffb/core/analyzer.py
ffb/core/run.py
ffb/helper/__init__.py
ffb/helper/stream_handler.py
ffb-0.1.1.dist-info/LICENSE
ffb-0.1.1.dist-info/METADATA
ffb-0.1.1.dist-info/WHEEL
ffb-0.1.1.dist-info/entry_points.txt
ffb-0.1.1.dist-info/top_level.txt
ffb-0.1.1.dist-info/RECORD
