Metadata-Version: 2.1
Name: ffb
Version: 0.1.1
Summary: Find Fucking Bug
Home-page: https://github.com/find-fucking-bug
Download-URL: https://github.com/find-fucking-bug
Author: Ali Yaman, Umut Deniz
Author-email: aliymn.db@gmail.com, umutdeniz609@gmail.com
License: MIT
Keywords: Find Fucking Bug,error handling,debugging tool
Classifier: Development Status :: 3 - Alpha
Classifier: Environment :: Console
Classifier: Intended Audience :: Developers
Classifier: Intended Audience :: Information Technology
Classifier: License :: OSI Approved :: MIT License
Classifier: Operating System :: OS Independent
Classifier: Programming Language :: Python :: 3
Classifier: Programming Language :: Python :: 3.6
Classifier: Programming Language :: Python :: 3.7
Classifier: Programming Language :: Python :: 3.8
Classifier: Programming Language :: Python :: 3.9
Classifier: Programming Language :: Python :: 3.10
Classifier: Programming Language :: Python :: 3.11
Classifier: Programming Language :: Python :: 3.12
Classifier: Topic :: Software Development
Classifier: Topic :: Software Development :: Debuggers
Classifier: Topic :: Software Development :: Quality Assurance
Classifier: Natural Language :: English
License-File: LICENSE
Requires-Dist: ollama ==0.3.2
Requires-Dist: rich ==13.8.0
